seleniuth/__init__.py
seleniuth-0.1.dist-info/LICENSE
seleniuth-0.1.dist-info/METADATA
seleniuth-0.1.dist-info/WHEEL
seleniuth-0.1.dist-info/top_level.txt
seleniuth-0.1.dist-info/RECORD
